{
  "version": "5.5.0",
  "flags": {},
  "shapes": [
    {
      "label": "0",
      "points": [
        [
          106.85714285714288,
          11.785714285714292
        ],
        [
          146.14285714285714,
          48.92857142857143
        ]
      ],
      "group_id": null,
      "description": "",
      "shape_type": "rectangle",
      "flags": {},
      "mask": null
    }
  ],
  "imagePath": "2f3bff3057e278aca45ef61d9e174bae-5.gif",
  "imageData": null,
  "imageHeight": 60,
  "imageWidth": 468
}